[{
    "name": "yaroslavwave",
    "paname": {
        "Хрещатий парк": "41079798",
        "Печерський ландшафтний парк": "23709143",
        "Печерський ландшафтний парк": "30914703",
        "Парк «Міський сад»": "30356317",
        "Парк «Міський сад»": "474649199",
        "Парк Шевченка": "444883195",
        "Ботанічний сад імені Олександра Фоміна": "444883195",
        "бульвар": "444883195",
        "Ботанічний сад імені Олександра Фоміна": "256474904",
        "Парк Шевченка": "23581536",
        "Вічної Слави парк": "41079798",
        "Наводницький парк": "30914703",
        "Хрещатий парк": "30356317",
        "Парк КПІ": "-4138136",
        "Парк Перемоги": "23705293"
    },
    "count": 375280
}, {
    "name": "sergey82k",
    "paname": {
        "Парк Шевченка": "444883195",
        "Парк Шевченка": "23581536",
        "Хрещатий парк": "30356317",
        "Ботанічний сад імені Олександра Фоміна": "256474904",
        "Ботанічний сад імені Олександра Фоміна": "444883195",
        "бульвар": "444883195",
        "Державний меморіал «Биківнянські могили»": "613952682",
        "Національний природний парк «Залісся»": "-6178989"
    },
    "count": 83540
}, {
    "name": "mapfool",
    "paname": {
        "Парк Шевченка": "23581536",
        "Золотоворітський сквер": "533851202",
        "Хрещатий парк": "41079798",
        "Маріїнський парк": "195071759",
        "Вічної Слави парк": "41079798",
        "Наводницький парк": "30914703",
        "Ботанічний сад імені Олександра Фоміна": "444883195",
        "Печерський ландшафтний парк": "23709143",
        "Печерський ландшафтний парк": "30914703",
        "Ботанічний сад імені Миколи Гришка": "100352601",
        "Хрещатий парк": "30356317",
        "бульвар": "444883195",
        "Золотоворітський сквер": "27830209",
        "Ботанічний сад імені Олександра Фоміна": "256474904",
        "Національний природний парк «Голосіївський»": "-1652168"
    },
    "count": 61350
}, {
    "name": "westbam",
    "paname": {
        "Парк КПІ": "-4200968",
        "Дубовий гай": "378507377",
        "Парк імені Пушкіна": "-4200968",
        "Парк «Нивки»": "378507377",
        "Золотоворітський сквер": "533851202",
        "Вічної Слави парк": "41079798",
        "Парк Шевченка": "444883195",
        "Святошинський лісопарк": "536291956",
        "Золотоворітський сквер": "27830209",
        "Заповідне урочище місцевого значення «Первомайське»": "-6211555",
        "Парк «Нивки»": "-4178379",
        "Ботанічний сад імені Олександра Фоміна": "444883195",
        "Хрещатий парк": "41079798",
        "бульвар": "444883195",
        "Парк Шевченка": "23581536",
        "Ботанічний сад імені Олександра Фоміна": "256474904",
        "Парк КПІ": "-4138136",
        "Хрещатий парк": "30356317",
        "Національний природний парк «Голосіївський»": "-1652168"
    },
    "count": 26830
}, {
    "name": "dvd1973",
    "paname": {
        "Региональный ландшафтный парк «Бакальская коса»": "360149803",
        "Ботанический заказник «Новый Свет»": "-2410811"
    },
    "count": 23410
}, {
    "name": "approksimator",
    "paname": {
        "Парк КПІ": "-4200968",
        "Парк «Міський сад»": "195071759",
        "Парк «Нивки»": "378507377",
        "Золотоворітський сквер": "533851202",
        "Ботанічний сад імені Миколи Гришка": "100352601",
        "Юність": "37853135",
        "Парк Шевченка": "444883195",
        "Дубовий гай": "378507377",
        "Золотоворітський сквер": "27830209",
        "Лісовий заказник місцевого значення «Гореницький»": "417010623",
        "Хрещатий парк": "195071759",
        "Парк імені Пушкіна": "-4200968",
        "Парк Шевченка": "23581536",
        "Парк «Міський сад»": "30356317",
        "Парк «Міський сад»": "474649199",
        "Ботанічний сад імені Олександра Фоміна": "256474904",
        "Ботанічний сад імені Олександра Фоміна": "444883195",
        "Хрещатий парк": "41079798",
        "Дубки": "-5637222",
        "бульвар": "444883195",
        "Парк КПІ": "-4138136",
        "Хрещатий парк": "30356317",
        "Національний природний парк «Голосіївський»": "-1652168",
        "Парк «Нивки»": "-4178379"
    },
    "count": 19210
}, {
    "name": "alekseyrm",
    "paname": {
        "Золотоворітський сквер": "533851202",
        "Золотоворітський сквер": "27830209",
        "Ландшафтний заказник загальнодержавного значення «Ржищівський»": "-6179142",
        "Національний природний парк «Голосіївський»": "-1652168",
        "Дендропарк «Олександрія»": "-1819246"
    },
    "count": 12170
}, {
    "name": "sergiy_petruha",
    "paname": {
        "Національний природний парк «Сколівські Бескиди»": "-2434313"
    },
    "count": 10150
}, {
    "name": "andergrin",
    "paname": {
        "Ботанічний сад «Вінницького національного аграрного університету»": "-5297702"
    },
    "count": 8050
}, {
    "name": "camarade",
    "paname": {
        "Парк КПІ": "-4138136",
        "Парк імені Пушкіна": "-4200968"
    },
    "count": 5260
}, {
    "name": "hast",
    "paname": {
        "Ботанічна пам'ятка природи «Пушкінська»": "360601201",
        "Регіональний ландшафтний парк «Сокольники-Помірки»": "360601313"
    },
    "count": 4100
}, {
    "name": "sapozhnik",
    "paname": {
        "Парк імені Пушкіна": "-4200968",
        "Відрадний": "32608259",
        "Парк «Нивки»": "-4178379"
    },
    "count": 3920
}, {
    "name": "wusel007",
    "paname": {
        "Зона відчуження Чорнобильської АЕС": "-3311547"
    },
    "count": 2710
}, {
    "name": "nikiforov",
    "paname": {
        "Залізні води": "-6160281",
        "Парк ім. Івана Франка": "165716010",
        "Стрийський парк": "-5423208"
    },
    "count": 2650
}, {
    "name": "saltuarius",
    "paname": {
        "Національний природний парк «Слобожанський»": "-3419143"
    },
    "count": 2650
}, {
    "name": "v_e_s",
    "paname": {
        "Національний природний парк «Бузький Гард»": "82962544"
    },
    "count": 2160
}, {
    "name": "healixx",
    "paname": {
        "Ландшафтний заказник «Берег річки»": "-5955296"
    },
    "count": 1890
}, {
    "name": "andreyhmk",
    "paname": {
        "Ботанічна пам'ятка природи «Інститутська»": "360601180",
        "Ботанічна пам'ятка природи «Будинок учених»": "360601183",
        "Ботанічна пам'ятка природи «Дуб Бабушкін»": "360601194",
        "Ботанічна пам'ятка природи «Пушкінська»": "360601201",
        "Ботанічна пам'ятка природи місцевого значення «Сокольники-Помірки»": "448012718",
        "Регіональний ландшафтний парк «Сокольники-Помірки»": "360601313"
    },
    "count": 1650
}, {
    "name": "nichiun",
    "paname": {
        "бульвар": "444883195",
        "Парк КПІ": "-4138136",
        "Ботанічний сад імені Олександра Фоміна": "444883195",
        "Ботанічний сад імені Олександра Фоміна": "256474904"
    },
    "count": 1010
}, {
    "name": "lenaviator",
    "paname": {
        "Дубовий гай": "378507377"
    },
    "count": 690
}, {
    "name": "ue0",
    "paname": {
        "Парк імені Пушкіна": "-4200968"
    },
    "count": 670
}, {
    "name": "irinka_21",
    "paname": {
        "Юність": "37853135",
        "Інтернаціональний": "37853135",
        "Парк «Нивки»": "378507377",
        "Інтернаціональний": "37568873",
        "Парк «Нивки»": "-4178379"
    },
    "count": 490
}, {
    "name": "shkolot",
    "paname": {
        "Ландшафтний заказник місцевого значення “Обухівський”": "-6199812"
    },
    "count": 440
}, {
    "name": "crazyfox.ua",
    "paname": {
        "Ботанічний сад імені Олександра Фоміна": "444883195",
        "Ботанічний сад імені Олександра Фоміна": "256474904"
    },
    "count": 180
}, {
    "name": "mihail_mihaylov",
    "paname": {
        "Ландшафтный заказник «Байдарский»": "-2410814"
    },
    "count": 100
}, {
    "name": "greyfish",
    "paname": {
        "Парк-пам'ятка садово-паркового мистецтва «Деребчинський парк»": "461366450"
    },
    "count": 60
}, {
    "name": "edwrddp",
    "paname": {
        "Дубовий гай": "378507377"
    },
    "count": 30
}, {
    "name": "bhop",
    "paname": {
        "Національний природний парк «Голосіївський»": "-1652168"
    },
    "count": 20
}]